{
    "created_time": "2021-03-24T08:38:11Z",
    "files": [
        {
            "attachment_folder": "",
            "created_time": "2021-03-24T08:38:11Z",
            "id": "0",
            "modified_time": "2021-05-22T08:19:39Z",
            "name": "KISS Dicom Viewer 体渲染插件（利用vtk Volume 实现体渲染）.md",
            "tags": [
            ]
        },
        {
            "attachment_folder": "",
            "created_time": "2021-03-24T08:38:11Z",
            "id": "0",
            "modified_time": "2021-05-22T08:21:28Z",
            "name": "(未完成) Study-VTK 体渲染学习.md",
            "tags": [
            ]
        },
        {
            "attachment_folder": "",
            "created_time": "2021-08-15T01:31:56Z",
            "id": "0",
            "modified_time": "2021-08-15T02:43:57Z",
            "name": "vtk 利用体渲染绘制地球.md",
            "tags": [
            ]
        }
    ],
    "folders": [
    ],
    "id": "0",
    "modified_time": "2021-03-24T08:38:11Z",
    "version": "1"
}
